{
  "formatVersion": 2,
  "id": "emodipt-extend",
  "name": "Emodipt Extend",
  "ui": {
    "crust": "#bc5b62",
    "mantle": "#e2737c",
    "base": "#e06c75",
    "surface0": "#e47e86",
    "surface1": "#e6868e",
    "surface2": "#e89299",
    "text": "#b8ff75",
    "subtext0": "#c5d075",
    "subtext1": "#bfe575",
    "overlay0": "#cdb375",
    "overlay1": "#c9c175",
    "blue": "#61afef",
    "lavender": "#9693bc",
    "green": "#b8ff75",
    "yellow": "#f3c267",
    "red": "#e06c75",
    "peach": "#e9936f",
    "teal": "#88d3b8",
    "sky": "#61afef",
    "mauve": "#e06c75"
  },
  "terminal": {
    "background": "#e06c75",
    "foreground": "#b8ff75",
    "cursor": "#b8ff75",
    "cursorAccent": "#e06c75",
    "selectionBackground": "rgba(137,180,250,0.28)",
    "black": "#e37b83",
    "red": "#e06c75",
    "green": "#b8ff75",
    "yellow": "#f3c267",
    "blue": "#61afef",
    "magenta": "#e06c75",
    "cyan": "#61afef",
    "white": "#bded75",
    "brightBlack": "#ceae75",
    "brightRed": "#e6868e",
    "brightGreen": "#c5ff8e",
    "brightYellow": "#f5cd82",
    "brightBlue": "#7dbdf2",
    "brightMagenta": "#e6868e",
    "brightCyan": "#7dbdf2",
    "brightWhite": "#b8ff75"
  }
}
