{
  "formatVersion": 2,
  "id": "nightfox-terafox",
  "name": "Nightfox Terafox",
  "ui": {
    "crust": "#121f22",
    "mantle": "#213033",
    "base": "#152528",
    "surface0": "#313f42",
    "surface1": "#3f4c4f",
    "surface2": "#525e60",
    "text": "#e6eaea",
    "subtext0": "#a3abac",
    "subtext1": "#c0c7c7",
    "overlay0": "#798485",
    "overlay1": "#8e9799",
    "blue": "#5a93aa",
    "lavender": "#73a3b7",
    "green": "#7aa4a1",
    "yellow": "#fda47f",
    "red": "#e85c51",
    "peach": "#fdb292",
    "teal": "#a1cdd8",
    "sky": "#afd4de",
    "mauve": "#ad5c7c"
  },
  "terminal": {
    "background": "#152528",
    "foreground": "#e6eaea",
    "cursor": "#e6eaea",
    "cursorAccent": "#152528",
    "selectionBackground": "#293e40",
    "black": "#2f3239",
    "red": "#e85c51",
    "green": "#7aa4a1",
    "yellow": "#fda47f",
    "blue": "#5a93aa",
    "magenta": "#ad5c7c",
    "cyan": "#a1cdd8",
    "white": "#ebebeb",
    "brightBlack": "#4e5157",
    "brightRed": "#eb746b",
    "brightGreen": "#8eb2af",
    "brightYellow": "#fdb292",
    "brightBlue": "#73a3b7",
    "brightMagenta": "#b97490",
    "brightCyan": "#afd4de",
    "brightWhite": "#eeeeee"
  }
}
