{
  "formatVersion": 2,
  "id": "poshmon",
  "name": "Poshmon",
  "ui": {
    "crust": "#000000",
    "mantle": "#0d0d0d",
    "base": "#000000",
    "surface0": "#1f1f1f",
    "surface1": "#2e2e2e",
    "surface2": "#424242",
    "text": "#ffffff",
    "subtext0": "#adadad",
    "subtext1": "#d1d1d1",
    "overlay0": "#7a7a7a",
    "overlay1": "#949494",
    "blue": "#306998",
    "lavender": "#75445f",
    "green": "#3c873a",
    "yellow": "#c19c00",
    "red": "#d51111",
    "peach": "#cc5009",
    "teal": "#348f6e",
    "sky": "#2e9599",
    "mauve": "#d51111"
  },
  "terminal": {
    "background": "#000000",
    "foreground": "#ffffff",
    "cursor": "#ffffff",
    "cursorAccent": "#000000",
    "selectionBackground": "rgba(137,180,250,0.28)",
    "black": "#1a1a1a",
    "red": "#d51111",
    "green": "#3c873a",
    "yellow": "#c19c00",
    "blue": "#306998",
    "magenta": "#d51111",
    "cyan": "#2e9599",
    "white": "#e0e0e0",
    "brightBlack": "#737373",
    "brightRed": "#dd3c3c",
    "brightGreen": "#5f9d5d",
    "brightYellow": "#ccae2e",
    "brightBlue": "#5584ab",
    "brightMagenta": "#dd3c3c",
    "brightCyan": "#54a8ab",
    "brightWhite": "#ffffff"
  }
}
