{
  "formatVersion": 2,
  "id": "zenbones-zenwritten-dark",
  "name": "Zenbones Zenwritten Dark",
  "ui": {
    "crust": "#151515",
    "mantle": "#252525",
    "base": "#191919",
    "surface0": "#353535",
    "surface1": "#424242",
    "surface2": "#555555",
    "text": "#bbbbbb",
    "subtext0": "#878787",
    "subtext1": "#9e9e9e",
    "overlay0": "#676767",
    "overlay1": "#777777",
    "blue": "#6099c0",
    "lavender": "#61abda",
    "green": "#819b69",
    "yellow": "#b77e64",
    "red": "#de6e7c",
    "peach": "#d68c67",
    "teal": "#66a5ad",
    "sky": "#65b8c1",
    "mauve": "#b279a7"
  },
  "terminal": {
    "background": "#191919",
    "foreground": "#bbbbbb",
    "cursor": "#c9c9c9",
    "cursorAccent": "#191919",
    "selectionBackground": "#404040",
    "black": "#191919",
    "red": "#de6e7c",
    "green": "#819b69",
    "yellow": "#b77e64",
    "blue": "#6099c0",
    "magenta": "#b279a7",
    "cyan": "#66a5ad",
    "white": "#bbbbbb",
    "brightBlack": "#3d3839",
    "brightRed": "#e8838f",
    "brightGreen": "#8bae68",
    "brightYellow": "#d68c67",
    "brightBlue": "#61abda",
    "brightMagenta": "#cf86c1",
    "brightCyan": "#65b8c1",
    "brightWhite": "#8e8e8e"
  }
}
